srt_to_vtt/__init__.py
srt_to_vtt/srt_to_vtt.py
srt_to_vtt-1.4.0.dist-info/LICENSE
srt_to_vtt-1.4.0.dist-info/METADATA
srt_to_vtt-1.4.0.dist-info/WHEEL
srt_to_vtt-1.4.0.dist-info/entry_points.txt
srt_to_vtt-1.4.0.dist-info/top_level.txt
srt_to_vtt-1.4.0.dist-info/RECORD
