Metadata-Version: 2.1
Name: srt-to-vtt
Version: 1.4.0
Summary: Python package to enable easy conversion of .srt files to .vtt files.
Author-email: Joshua Hamilton <hamiltonjoshuadavid@gmail.com>
License: MIT License
Project-URL: homepage, https://github.com/joshdavham/srt-to-vtt
Keywords: subtitle,subtitles,convert,srt,vtt,webvtt
Classifier: Programming Language :: Python :: 3
Classifier: License :: OSI Approved :: MIT License
Classifier: Operating System :: OS Independent
Requires-Python: >=3.9
License-File: LICENSE
